{
  "arch": "arm64",
  "build": "hca03da5_6",
  "build_number": 6,
  "channel": "https://repo.anaconda.com/pkgs/main/osx-arm64",
  "constrains": [],
  "depends": [],
  "features": "",
  "fn": "libffi-3.4.2-hca03da5_6.conda",
  "legacy_bz2_md5": "61990ec0f3b6b3ac2dceb51aa4812187",
  "license": "MIT",
  "license_family": "MIT",
  "md5": "3f6a38442ba0fd3d273dc9127a761272",
  "name": "libffi",
  "platform": "darwin",
  "sha256": "a2d993bba01ce818c4496f12da6445a63705d5e065811b86817262fb70f98fa4",
  "size": 117496,
  "subdir": "osx-arm64",
  "timestamp": 1669126652493,
  "track_features": "",
  "url": "https://repo.anaconda.com/pkgs/main/osx-arm64/libffi-3.4.2-hca03da5_6.conda",
  "version": "3.4.2"
}